{"108992": [["/thumb/4d481/profile.jpg", "Emily Jackson"]], "70448": [["/thumb/2f4c2/profile.jpg", "Ava Martin"]], "58384": [["/thumb/a8cf4/profile.jpg", "Jayden Smith"]], "83440": [["/thumb/0ce3c/profile.jpg", "Joseph Jones"], ["/thumb/4cb6b/profile.jpg", "Isabella Thomas"]], "68032": [["/thumb/4a35a/profile.jpg", "Mateo Jackson"]], "60608": [["/thumb/76e38/profile.jpg", "Mason Brown"]], "109056": [["/thumb/b6952/profile.jpg", "James Lopez"]], "64848": [["/thumb/eaf9a/profile.jpg", "Mary Martin"], ["/thumb/cb82b/profile.jpg", "Sofia Wilson"]], "112608": [["/thumb/666e3/profile.jpg", "Mia Martinez"]], "90720": [["/thumb/8fbfc/profile.jpg", "Ava Lopez"], ["/thumb/c29f7/profile.jpg", "Ava Williams"]], "54736": [["/thumb/e0c30/profile.jpg", "David Smith"], ["/thumb/e822f/profile.jpg", "Ethan Johnson"]], "55536": [["/thumb/8a854/profile.jpg", "Noah Martin"]], "116416": [["/thumb/f0c46/profile.jpg", "Noah Hernandez"]], "75424": [["/thumb/e8bd7/profile.jpg", "Joseph Thomas"]], "65280": [["/thumb/46e2d/profile.jpg", "Ethan Hernandez"]], "123168": [["/thumb/0fd8c/profile.jpg", "Noah Lopez"]], "105312": [["/thumb/0d7af/profile.jpg", "Olivia White"]], "71984": [["/thumb/52b45/profile.jpg", "Isabella Davis"]], "80720": [["/thumb/9ed3e/profile.jpg", "Mateo White"]], "79136": [["/thumb/7e1d4/profile.jpg", "Noah Davis"]], "86960": [["/thumb/ef2b0/profile.jpg", "David Brown"], ["/thumb/8d8c5/profile.jpg", "Chloe Lopez"]], "77760": [["/thumb/096f9/profile.jpg", "Mary Rodriquez"]], "84544": [["/thumb/2d522/profile.jpg", "Santiago Martinez"]], "44512": [["/thumb/f2359/profile.jpg", "Ethan Rodriquez"]], "51600": [["/thumb/d59b0/profile.jpg", "Madison Johnson"]], "64704": [["/thumb/12d5a/profile.jpg", "Mason Brown"]], "78400": [["/thumb/73189/profile.jpg", "Anya Wilson"], ["/thumb/4d335/profile.jpg", "Mateo Anderson"]], "46096": [["/thumb/73a8b/profile.jpg", "Shreya Garcia"]], "69072": [["/thumb/433e1/profile.jpg", "Ethan Lee"]], "61856": [["/thumb/b39ef/profile.jpg", "Jayden Lee"]], "90944": [["/thumb/ed6ec/profile.jpg", "David Hernandez"]], "80592": [["/thumb/28f4b/profile.jpg", "Anya Rodriquez"]], "77616": [["/thumb/2ada1/profile.jpg", "Mateo Johnson"]], "107104": [["/thumb/d59cd/profile.jpg", "Sofia Thomas"]], "57616": [["/thumb/e57cc/profile.jpg", "Ethan Williams"]], "69776": [["/thumb/5a180/profile.jpg", "Deven Jackson"]], "79040": [["/thumb/ca9bd/profile.jpg", "Mia Martinez"]], "288416": [["/thumb/b2603/profile.jpg", "Noah Smith"]], "79664": [["/thumb/c7822/profile.jpg", "Mason Rodriquez"]], "134912": [["/thumb/78a11/profile.jpg", "Deven Johnson"]], "70096": [["/thumb/0ff23/profile.jpg", "Joseph Miller"]], "52528": [["/thumb/8705a/profile.jpg", "Emily Miller"]], "90224": [["/thumb/09e3f/profile.jpg", "Barbara Jones"]], "103760": [["/thumb/e0a64/profile.jpg", "Liam Moore"]], "109488": [["/thumb/0eae0/profile.jpg", "Emily White"]], "79344": [["/thumb/f4ec2/profile.jpg", "Deven Lopez"]], "66224": [["/thumb/f3537/profile.jpg", "Sofia Johnson"]], "53024": [["/thumb/a1219/profile.jpg", "Emma Miller"]], "76528": [["/thumb/ceae4/profile.jpg", "Shreya Jones"], ["/thumb/1eb4a/profile.jpg", "Deven White"]], "70240": [["/thumb/003c8/profile.jpg", "Emily Hernandez"], ["/thumb/01720/profile.jpg", "Mary Thomas"]], "68768": [["/thumb/3558e/profile.jpg", "Madison Moore"]], "63440": [["/thumb/ce48b/profile.jpg", "Mia Hernandez"]], "76848": [["/thumb/9e9f4/profile.jpg", "Barbara White"]], "69856": [["/thumb/ea6d6/profile.jpg", "Ethan Smith"]], "75808": [["/thumb/d8f58/profile.jpg", "Isabella Jones"]], "60720": [["/thumb/5fdd9/profile.jpg", "Mary Lopez"]], "50128": [["/thumb/863aa/profile.jpg", "Anya Martin"]], "57376": [["/thumb/0adc0/profile.jpg", "David Jackson"]], "66032": [["/thumb/a7e3f/profile.jpg", "Jacob Moore"]], "71424": [["/thumb/9fe9c/profile.jpg", "Chloe Rodriquez"]], "56176": [["/thumb/334f1/profile.jpg", "Ethan Williams"]], "75504": [["/thumb/53fbf/profile.jpg", "Santiago Williams"]], "110192": [["/thumb/67e7d/profile.jpg", "Mason Jackson"]], "88192": [["/thumb/4d431/profile.jpg", "Shreya Lee"]], "73024": [["/thumb/28e68/profile.jpg", "Mia Brown"]], "106144": [["/thumb/66af7/profile.jpg", "Olivia Garcia"]], "78880": [["/thumb/29b9e/profile.jpg", "Deven Martinez"]], "60944": [["/thumb/8a6e1/profile.jpg", "Madison Wilson"]], "96560": [["/thumb/7d2f1/profile.jpg", "Chloe Jones"]], "78544": [["/thumb/9769f/profile.jpg", "David Miller"]], "59920": [["/thumb/c047b/profile.jpg", "David Smith"]], "55872": [["/thumb/3608b/profile.jpg", "Mia Rodriquez"]], "74576": [["/thumb/1ea4c/profile.jpg", "Ethan Johnson"]], "142480": [["/thumb/45407/profile.jpg", "Mason White"]], "79760": [["/thumb/8bbdb/profile.jpg", "Jayden Jackson"]], "62160": [["/thumb/32462/profile.jpg", "David Hernandez"]], "120000": [["/thumb/206dd/profile.jpg", "Mia Taylor"]], "51152": [["/thumb/7a2e6/profile.jpg", "Olivia Williams"]], "93568": [["/thumb/627b3/profile.jpg", "Ethan Smith"]], "64544": [["/thumb/bb532/profile.jpg", "Ethan Moore"]], "81392": [["/thumb/b6fae/profile.jpg", "Olivia Wilson"]], "67440": [["/thumb/078e4/profile.jpg", "Ava Brown"], ["/thumb/af8a2/profile.jpg", "Noah White"]], "64464": [["/thumb/e2954/profile.jpg", "Mia Martinez"]], "60048": [["/thumb/a972f/profile.jpg", "Ethan Smith"]], "107008": [["/thumb/6de62/profile.jpg", "Mason Anderson"]], "75712": [["/thumb/9e4e7/profile.jpg", "Madison Martin"]], "74176": [["/thumb/1be1a/profile.jpg", "Mary Wilson"]], "75488": [["/thumb/05c44/profile.jpg", "Mary Davis"]], "64496": [["/thumb/ac59d/profile.jpg", "Deven Martin"]], "148352": [["/thumb/f9180/profile.jpg", "Mason Martinez"]], "99920": [["/thumb/1e4c7/profile.jpg", "Shreya Brown"]], "131360": [["/thumb/bf3a3/profile.jpg", "Santiago Brown"]], "43168": [["/thumb/00285/profile.jpg", "Shreya Williams"]], "72048": [["/thumb/5e67e/profile.jpg", "Mateo Garcia"]], "64080": [["/thumb/c2b11/profile.jpg", "Ethan Davis"]], "91968": [["/thumb/1f919/profile.jpg", "Liam Moore"]], "84992": [["/thumb/a9d80/profile.jpg", "Madison Martinez"]], "82112": [["/thumb/0b36d/profile.jpg", "Ava Davis"]], "87808": [["/thumb/d2762/profile.jpg", "Barbara Garcia"]], "56896": [["/thumb/24b77/profile.jpg", "Mary Martinez"]], "70112": [["/thumb/db136/profile.jpg", "Ethan Brown"]], "91568": [["/thumb/7eb15/profile.jpg", "Sofia White"]], "236608": [["/thumb/3f818/profile.jpg", "Olivia Davis"]], "64480": [["/thumb/0fe8a/profile.jpg", "Isabella White"]], "46992": [["/thumb/cf965/profile.jpg", "Joseph Brown"]], "79232": [["/thumb/667c9/profile.jpg", "David Garcia"]], "62944": [["/thumb/686ad/profile.jpg", "Ava Rodriquez"]], "42768": [["/thumb/a9f5f/profile.jpg", "Emma Rodriquez"]], "78960": [["/thumb/9de10/profile.jpg", "Ethan Thomas"]], "77056": [["/thumb/810ff/profile.jpg", "Noah Davis"]], "90032": [["/thumb/545cd/profile.jpg", "Mason Johnson"]], "85728": [["/thumb/f6069/profile.jpg", "Noah Johnson"]], "59712": [["/thumb/91988/profile.jpg", "Mateo White"]], "217440": [["/thumb/77fbf/profile.jpg", "Emma Martin"]], "49824": [["/thumb/ef07c/profile.jpg", "Joseph Williams"]], "43344": [["/thumb/08e41/profile.jpg", "Mateo Jackson"]], "76656": [["/thumb/2e39f/profile.jpg", "James Thomas"]], "87504": [["/thumb/4793c/profile.jpg", "Olivia Thomas"]], "93632": [["/thumb/e931e/profile.jpg", "Emily Wilson"]], "192528": [["/thumb/13854/profile.jpg", "Mia Lee"]], "70752": [["/thumb/fc4c7/profile.jpg", "Joseph Smith"]], "43936": [["/thumb/24def/profile.jpg", "Emily Martin"]], "74432": [["/thumb/335ed/profile.jpg", "Liam Miller"]], "169792": [["/thumb/88e39/profile.jpg", "Emma White"]], "65264": [["/thumb/20fc3/profile.jpg", "Mateo Thomas"]], "55520": [["/thumb/399f8/profile.jpg", "Ava White"]], "122832": [["/thumb/74b13/profile.jpg", "Deven Martin"]], "73072": [["/thumb/0fa74/profile.jpg", "Ethan Martin"]], "270976": [["/thumb/2187a/profile.jpg", "Anya Garcia"]], "42192": [["/thumb/6dfe3/profile.jpg", "Emma Johnson"]], "52928": [["/thumb/b8cba/profile.jpg", "David Hernandez"]], "141024": [["/thumb/c7e96/profile.jpg", "Liam Martin"]], "120048": [["/thumb/323e2/profile.jpg", "Noah Davis"]], "84208": [["/thumb/7943c/profile.jpg", "James Smith"]], "99328": [["/thumb/670a3/profile.jpg", "Santiago Jones"]], "67248": [["/thumb/8d671/profile.jpg", "Mason Wilson"]], "57264": [["/thumb/b5589/profile.jpg", "John Lopez"]], "76432": [["/thumb/c929a/profile.jpg", "Olivia Wilson"]], "86704": [["/thumb/2ca8b/profile.jpg", "Mary Taylor"]], "71888": [["/thumb/6b305/profile.jpg", "Mary Taylor"]], "58768": [["/thumb/4cbeb/profile.jpg", "Ava Martin"]], "79696": [["/thumb/3c0cf/profile.jpg", "Mary Lopez"]], "69984": [["/thumb/b9e4a/profile.jpg", "James Miller"], ["/thumb/92bda/profile.jpg", "Noah Brown"]], "67664": [["/thumb/75363/profile.jpg", "Mason Rodriquez"]], "68544": [["/thumb/f923a/profile.jpg", "Jayden Moore"]], "66128": [["/thumb/25d88/profile.jpg", "Jayden Taylor"], ["/thumb/c43e9/profile.jpg", "Emma Davis"]], "126224": [["/thumb/de11f/profile.jpg", "Barbara Jones"]], "46272": [["/thumb/120f0/profile.jpg", "Anya Anderson"]], "116752": [["/thumb/40adb/profile.jpg", "Emma Taylor"]], "124720": [["/thumb/b38c4/profile.jpg", "Emma Smith"]], "102432": [["/thumb/d44b5/profile.jpg", "Joseph Williams"]], "152832": [["/thumb/3f22c/profile.jpg", "Emma Hernandez"]], "80064": [["/thumb/80155/profile.jpg", "Joseph Hernandez"]], "84112": [["/thumb/395e9/profile.jpg", "Jayden Williams"]], "57104": [["/thumb/291de/profile.jpg", "Mason Martinez"]], "77808": [["/thumb/870b0/profile.jpg", "Noah White"]], "67488": [["/thumb/4d43d/profile.jpg", "Jacob Rodriquez"]], "72912": [["/thumb/476d3/profile.jpg", "Madison Rodriquez"]], "78800": [["/thumb/4c82c/profile.jpg", "Madison Davis"]], "72160": [["/thumb/5a2d7/profile.jpg", "Ava Martin"]], "54560": [["/thumb/6631d/profile.jpg", "Emma Martinez"]], "83056": [["/thumb/26cac/profile.jpg", "Barbara Johnson"]], "68160": [["/thumb/a58d3/profile.jpg", "Emma Thomas"]], "46976": [["/thumb/21c98/profile.jpg", "James Rodriquez"]], "121072": [["/thumb/bea6d/profile.jpg", "Barbara Lee"]], "48384": [["/thumb/c2d5b/profile.jpg", "Mary Garcia"]], "59216": [["/thumb/3823b/profile.jpg", "Chloe White"]], "36016": [["/thumb/02851/profile.jpg", "Mason Lee"]], "80368": [["/thumb/8eb8e/profile.jpg", "Anya Johnson"]], "54960": [["/thumb/26933/profile.jpg", "Mary Lopez"]], "90672": [["/thumb/58639/profile.jpg", "Olivia Jackson"]], "62976": [["/thumb/0f1cd/profile.jpg", "Ethan Martinez"], ["/thumb/0183d/profile.jpg", "Ava Jackson"]], "54416": [["/thumb/49583/profile.jpg", "Anya Hernandez"]], "48256": [["/thumb/2ed45/profile.jpg", "Shreya Johnson"]], "71520": [["/thumb/746f6/profile.jpg", "Mia Martin"]], "119712": [["/thumb/4a61b/profile.jpg", "James Lopez"]], "84240": [["/thumb/8a800/profile.jpg", "Joseph Lopez"]], "96592": [["/thumb/61d91/profile.jpg", "Santiago White"]], "101216": [["/thumb/f95bf/profile.jpg", "Deven Lee"]], "122784": [["/thumb/94ca9/profile.jpg", "Joseph Anderson"]], "71488": [["/thumb/d8b71/profile.jpg", "Jacob Johnson"]], "102768": [["/thumb/f12c1/profile.jpg", "Jayden Hernandez"]], "70336": [["/thumb/e6933/profile.jpg", "Deven Martin"]], "92992": [["/thumb/ffa2a/profile.jpg", "Emily Jones"]], "78496": [["/thumb/e293a/profile.jpg", "Anya Moore"]], "75408": [["/thumb/c00e8/profile.jpg", "Mason Martin"]], "56640": [["/thumb/c0f81/profile.jpg", "Olivia Anderson"]], "58336": [["/thumb/860ce/profile.jpg", "Emily Davis"]], "62096": [["/thumb/e19ee/profile.jpg", "Joseph Johnson"]], "87696": [["/thumb/0ebd5/profile.jpg", "Anya Anderson"]], "115712": [["/thumb/cf28c/profile.jpg", "Mia Garcia"]], "58720": [["/thumb/15015/profile.jpg", "Chloe Rodriquez"]], "119760": [["/thumb/7daef/profile.jpg", "Jacob Jackson"]], "93392": [["/thumb/10484/profile.jpg", "Shreya Smith"]], "74864": [["/thumb/8cc29/profile.jpg", "Anya Jones"]], "99888": [["/thumb/39cc3/profile.jpg", "Mateo Moore"]], "76640": [["/thumb/eed1d/profile.jpg", "Sofia Hernandez"]], "76464": [["/thumb/186b1/profile.jpg", "Mia Lee"]], "78720": [["/thumb/c6156/profile.jpg", "David Martin"]], "49536": [["/thumb/86770/profile.jpg", "Mason Smith"]], "91280": [["/thumb/5f379/profile.jpg", "Liam Davis"]], "50368": [["/thumb/82deb/profile.jpg", "Jayden Davis"]], "66272": [["/thumb/645fe/profile.jpg", "Noah Lopez"]], "60288": [["/thumb/7b1b8/profile.jpg", "James Hernandez"]], "63952": [["/thumb/8a255/profile.jpg", "Madison Brown"]], "111120": [["/thumb/51874/profile.jpg", "Emma Taylor"]], "77568": [["/thumb/067dc/profile.jpg", "Jayden Taylor"]], "72240": [["/thumb/4d320/profile.jpg", "Emma Wilson"]], "85520": [["/thumb/10011/profile.jpg", "Santiago Martin"]], "66400": [["/thumb/a4196/profile.jpg", "Madison Jones"]], "60752": [["/thumb/d6276/profile.jpg", "Mason Jones"], ["/thumb/b7c89/profile.jpg", "Barbara Lee"]], "84144": [["/thumb/357da/profile.jpg", "David Moore"]], "86128": [["/thumb/32ea1/profile.jpg", "Olivia Jones"]], "87744": [["/thumb/37f72/profile.jpg", "Sofia Hernandez"]], "64384": [["/thumb/3ce62/profile.jpg", "Barbara Garcia"]], "52144": [["/thumb/ca753/profile.jpg", "Madison White"]], "174464": [["/thumb/c0774/profile.jpg", "Jacob Taylor"]], "67472": [["/thumb/92673/profile.jpg", "David Taylor"]], "53760": [["/thumb/1cda4/profile.jpg", "Ethan Lopez"]], "104768": [["/thumb/87b0d/profile.jpg", "Mason Garcia"]], "122848": [["/thumb/57a1e/profile.jpg", "Jayden Jones"]], "74640": [["/thumb/1a9d8/profile.jpg", "Mary Jackson"], ["/thumb/c2a8d/profile.jpg", "Barbara Moore"]], "126400": [["/thumb/f3c8b/profile.jpg", "Jayden Davis"]], "61120": [["/thumb/f8277/profile.jpg", "Mason Rodriquez"]], "62992": [["/thumb/7ec7f/profile.jpg", "Chloe Moore"]], "52800": [["/thumb/ae7ed/profile.jpg", "Santiago Lee"]], "211472": [["/thumb/3a789/profile.jpg", "Anya Davis"]], "82032": [["/thumb/75a9a/profile.jpg", "Noah Martinez"]], "105488": [["/thumb/4cf78/profile.jpg", "Liam Smith"]], "74928": [["/thumb/173f1/profile.jpg", "James Martinez"]], "82896": [["/thumb/2e16e/profile.jpg", "David Martinez"]], "264128": [["/thumb/dab1a/profile.jpg", "Liam Lopez"]], "75520": [["/thumb/1a2cb/profile.jpg", "Emma Anderson"]], "70944": [["/thumb/bb74d/profile.jpg", "Madison Anderson"], ["/thumb/57926/profile.jpg", "Olivia Lee"], ["/thumb/c8ed8/profile.jpg", "Emma Miller"]], "123344": [["/thumb/73e76/profile.jpg", "James Jackson"]], "83664": [["/thumb/52164/profile.jpg", "Chloe Thomas"]], "99760": [["/thumb/c0ffb/profile.jpg", "Mason Anderson"]], "70464": [["/thumb/6279a/profile.jpg", "Ava Smith"]], "73440": [["/thumb/0f204/profile.jpg", "Olivia Taylor"]], "51216": [["/thumb/e4809/profile.jpg", "Chloe Johnson"], ["/thumb/66438/profile.jpg", "Joseph Anderson"]], "40032": [["/thumb/cd247/profile.jpg", "Emily Martinez"]], "60800": [["/thumb/f9083/profile.jpg", "Deven Hernandez"]], "96400": [["/thumb/5ae9d/profile.jpg", "Ethan Smith"]], "98112": [["/thumb/5c0e9/profile.jpg", "David Davis"]], "62064": [["/thumb/8cb69/profile.jpg", "James Johnson"]], "56288": [["/thumb/12f44/profile.jpg", "Mateo Brown"]], "50208": [["/thumb/09588/profile.jpg", "Joseph Lee"]], "108416": [["/thumb/b0ad6/profile.jpg", "Mateo Lee"]], "74512": [["/thumb/a3929/profile.jpg", "Anya Taylor"]], "87648": [["/thumb/fbc9a/profile.jpg", "Liam Martinez"]], "94528": [["/thumb/247de/profile.jpg", "Joseph Jones"]], "135168": [["/thumb/a503f/profile.jpg", "Ava Anderson"]], "77632": [["/thumb/ccf02/profile.jpg", "Deven Lopez"]], "76320": [["/thumb/9ee8c/profile.jpg", "David Martinez"]], "78512": [["/thumb/1a443/profile.jpg", "Madison Martin"]], "76736": [["/thumb/c4b5b/profile.jpg", "Shreya Lopez"]], "91792": [["/thumb/6a3bb/profile.jpg", "Mateo Johnson"], ["/thumb/c1204/profile.jpg", "Jacob Thomas"]], "30000": [["/thumb/efc55/profile.jpg", "Emily White"]], "67424": [["/thumb/d2bff/profile.jpg", "Olivia Taylor"]], "89184": [["/thumb/b8948/profile.jpg", "Isabella Miller"]], "120896": [["/thumb/691c5/profile.jpg", "Shreya Martin"]], "50720": [["/thumb/55276/profile.jpg", "John Hernandez"]], "91648": [["/thumb/26984/profile.jpg", "Chloe Jackson"]], "59056": [["/thumb/ac6e5/profile.jpg", "Emma Jones"]], "81008": [["/thumb/cfe8d/profile.jpg", "Emma Thomas"]], "57072": [["/thumb/39509/profile.jpg", "Olivia Thomas"]], "96816": [["/thumb/9ae87/profile.jpg", "Mason Lee"]], "66592": [["/thumb/cea31/profile.jpg", "Ethan Thomas"]], "68112": [["/thumb/95302/profile.jpg", "Madison Williams"]], "64320": [["/thumb/5641a/profile.jpg", "Ethan Rodriquez"]], "64240": [["/thumb/17915/profile.jpg", "Emily Taylor"]], "49712": [["/thumb/b9497/profile.jpg", "James Jones"]], "46688": [["/thumb/6e398/profile.jpg", "Ethan Brown"]], "72688": [["/thumb/7909e/profile.jpg", "Jayden Thomas"]], "88464": [["/thumb/d1cf8/profile.jpg", "Santiago Thomas"]], "56976": [["/thumb/2149c/profile.jpg", "Mary Williams"]], "61760": [["/thumb/27b02/profile.jpg", "James Taylor"]], "87792": [["/thumb/f7647/profile.jpg", "Sofia Wilson"], ["/thumb/e2b51/profile.jpg", "Shreya Jackson"]], "103632": [["/thumb/47ac8/profile.jpg", "John Lee"]], "72864": [["/thumb/10b95/profile.jpg", "Noah Moore"]], "62960": [["/thumb/d60f8/profile.jpg", "Sofia Smith"]], "50928": [["/thumb/6468e/profile.jpg", "Liam Martin"]], "70640": [["/thumb/e7255/profile.jpg", "Emma Lee"]], "70528": [["/thumb/bfdb2/profile.jpg", "Ava White"]], "118384": [["/thumb/4cc70/profile.jpg", "Barbara Martinez"]], "92160": [["/thumb/13cb1/profile.jpg", "Madison Brown"]], "102880": [["/thumb/b0180/profile.jpg", "Emily Garcia"]], "71920": [["/thumb/1ff5f/profile.jpg", "Noah Anderson"]], "104944": [["/thumb/377ac/profile.jpg", "Mia Miller"]], "44688": [["/thumb/712e1/profile.jpg", "Joseph Wilson"]], "43264": [["/thumb/9d28d/profile.jpg", "Noah Rodriquez"]], "84928": [["/thumb/277c2/profile.jpg", "Deven Smith"]], "82736": [["/thumb/f9a01/profile.jpg", "Olivia Hernandez"]], "70720": [["/thumb/1f877/profile.jpg", "Ethan Thomas"]], "70736": [["/thumb/d86b8/profile.jpg", "Emily Miller"]], "73488": [["/thumb/d31ab/profile.jpg", "John Rodriquez"]], "85776": [["/thumb/5fb44/profile.jpg", "Joseph Hernandez"]], "87952": [["/thumb/6da14/profile.jpg", "Liam Hernandez"]], "79920": [["/thumb/07e22/profile.jpg", "Ava Lopez"]], "59088": [["/thumb/60986/profile.jpg", "Mary Lee"]], "137200": [["/thumb/04b3b/profile.jpg", "Ethan Garcia"]], "56320": [["/thumb/72862/profile.jpg", "David Moore"]], "58304": [["/thumb/96a57/profile.jpg", "Mia Lee"]], "128960": [["/thumb/ab36b/profile.jpg", "Mary White"]], "96144": [["/thumb/e7973/profile.jpg", "Deven Jones"]], "86208": [["/thumb/42d06/profile.jpg", "James Moore"]], "81152": [["/thumb/e6b7d/profile.jpg", "Olivia Jackson"], ["/thumb/85569/profile.jpg", "Santiago White"]], "67168": [["/thumb/6d5bc/profile.jpg", "David Hernandez"]], "70880": [["/thumb/d1b70/profile.jpg", "Shreya Garcia"]], "82592": [["/thumb/4b463/profile.jpg", "Shreya Davis"]], "84224": [["/thumb/3a862/profile.jpg", "Shreya Jones"], ["/thumb/cd2c3/profile.jpg", "Liam White"], ["/thumb/4a841/profile.jpg", "Emily White"]], "102176": [["/thumb/2e361/profile.jpg", "Emily Wilson"]], "97168": [["/thumb/8a110/profile.jpg", "Mateo Smith"], ["/thumb/2d064/profile.jpg", "Emily Davis"]], "78000": [["/thumb/047dd/profile.jpg", "Emily Smith"]], "65968": [["/thumb/b690a/profile.jpg", "Joseph Wilson"]], "67040": [["/thumb/f0d60/profile.jpg", "John Lopez"]], "83024": [["/thumb/3d013/profile.jpg", "Ethan Martinez"]], "135184": [["/thumb/ca17a/profile.jpg", "Deven Thomas"]], "76512": [["/thumb/2d1b8/profile.jpg", "Ava Jones"]], "46320": [["/thumb/aa316/profile.jpg", "John White"]], "56864": [["/thumb/77c3e/profile.jpg", "Jacob Garcia"]], "52016": [["/thumb/23905/profile.jpg", "Barbara Anderson"]], "40624": [["/thumb/5791b/profile.jpg", "Olivia Garcia"]], "56800": [["/thumb/09b06/profile.jpg", "David Moore"]], "64960": [["/thumb/e44a7/profile.jpg", "Olivia Smith"]], "47936": [["/thumb/114cb/profile.jpg", "Jayden Johnson"]], "80608": [["/thumb/0786e/profile.jpg", "Joseph Moore"]], "110816": [["/thumb/9f67b/profile.jpg", "James Davis"]], "78640": [["/thumb/25b7a/profile.jpg", "Jacob Martinez"]], "69312": [["/thumb/48282/profile.jpg", "Mason Williams"], ["/thumb/b9b3d/profile.jpg", "Anya Brown"]], "64144": [["/thumb/7a0e2/profile.jpg", "Mia Davis"]], "80192": [["/thumb/ef6c1/profile.jpg", "Sofia Lee"]], "105792": [["/thumb/725e9/profile.jpg", "Jacob Rodriquez"]], "46928": [["/thumb/25978/profile.jpg", "John Garcia"]], "64048": [["/thumb/a5a9b/profile.jpg", "Sofia Davis"]], "42624": [["/thumb/40de9/profile.jpg", "Santiago Lee"]], "89792": [["/thumb/f804c/profile.jpg", "Sofia Taylor"]], "45696": [["/thumb/ee600/profile.jpg", "Emily Moore"]], "38400": [["/thumb/0b6a3/profile.jpg", "James White"]], "79968": [["/thumb/a4f4d/profile.jpg", "Emily Jones"]], "43616": [["/thumb/3a223/profile.jpg", "John Wilson"]], "111968": [["/thumb/e3cc7/profile.jpg", "Santiago Miller"]], "77824": [["/thumb/bdcc1/profile.jpg", "David Wilson"]], "69168": [["/thumb/dfb74/profile.jpg", "Mateo Martinez"]], "70256": [["/thumb/505b6/profile.jpg", "Olivia Smith"]], "128112": [["/thumb/97799/profile.jpg", "Joseph Johnson"]], "54544": [["/thumb/dde37/profile.jpg", "Santiago Thomas"]], "63456": [["/thumb/a1255/profile.jpg", "Anya Brown"]], "53632": [["/thumb/1caac/profile.jpg", "John Martin"]], "48848": [["/thumb/6eb38/profile.jpg", "Santiago White"]], "84688": [["/thumb/6a579/profile.jpg", "Shreya White"]], "66896": [["/thumb/92423/profile.jpg", "Mason Martinez"]], "84048": [["/thumb/fbe30/profile.jpg", "Mia Johnson"]], "61040": [["/thumb/b12f9/profile.jpg", "Madison Brown"]], "74848": [["/thumb/9d502/profile.jpg", "Chloe White"]], "104912": [["/thumb/0bd8d/profile.jpg", "Santiago Williams"]], "70400": [["/thumb/abf46/profile.jpg", "Sofia Smith"]], "65200": [["/thumb/4795a/profile.jpg", "Ethan Garcia"]], "150512": [["/thumb/3cce8/profile.jpg", "Sofia Taylor"]], "71136": [["/thumb/02798/profile.jpg", "Noah Rodriquez"]], "35664": [["/thumb/75bc0/profile.jpg", "Jacob Smith"]], "53520": [["/thumb/09481/profile.jpg", "Noah Hernandez"]], "69696": [["/thumb/4caf6/profile.jpg", "Mateo Thomas"]], "53440": [["/thumb/40f72/profile.jpg", "Mateo Thomas"]], "73056": [["/thumb/8a99f/profile.jpg", "Liam Lee"], ["/thumb/e6469/profile.jpg", "Shreya Thomas"]], "48016": [["/thumb/e2c5e/profile.jpg", "John Johnson"]], "71408": [["/thumb/9f516/profile.jpg", "Shreya Thomas"]], "44480": [["/thumb/35d36/profile.jpg", "Emma Lopez"]], "133584": [["/thumb/3f1d0/profile.jpg", "Madison Johnson"]], "99456": [["/thumb/e35f0/profile.jpg", "Emma Hernandez"]], "76928": [["/thumb/bca53/profile.jpg", "Deven Lopez"]], "81440": [["/thumb/7d323/profile.jpg", "Anya Martinez"]], "78896": [["/thumb/b76ff/profile.jpg", "Madison Thomas"]], "40128": [["/thumb/7ac9a/profile.jpg", "Olivia Taylor"]], "78352": [["/thumb/adf00/profile.jpg", "Shreya Rodriquez"], ["/thumb/c4557/profile.jpg", "Mason White"]], "104256": [["/thumb/972ee/profile.jpg", "Ava Anderson"]], "69280": [["/thumb/7c7ff/profile.jpg", "Jayden Moore"]], "175392": [["/thumb/bd888/profile.jpg", "David Wilson"]], "57792": [["/thumb/d65c4/profile.jpg", "Mary Martinez"]], "68960": [["/thumb/62235/profile.jpg", "Olivia Moore"]], "94064": [["/thumb/0ae0d/profile.jpg", "Emma Jackson"]], "67632": [["/thumb/34d06/profile.jpg", "Olivia Thomas"]], "60256": [["/thumb/14a0a/profile.jpg", "Sofia Martinez"]], "77648": [["/thumb/0db28/profile.jpg", "Joseph Lee"]], "244288": [["/thumb/80528/profile.jpg", "Santiago Martin"]], "79072": [["/thumb/6919e/profile.jpg", "Mia Brown"]], "91408": [["/thumb/42cae/profile.jpg", "Noah Taylor"]], "77728": [["/thumb/09f5e/profile.jpg", "Santiago Garcia"], ["/thumb/e7215/profile.jpg", "Noah Brown"], ["/thumb/28426/profile.jpg", "David Anderson"]], "86880": [["/thumb/b331f/profile.jpg", "Ethan Williams"]], "129440": [["/thumb/1cd17/profile.jpg", "Jayden Thomas"]], "69216": [["/thumb/9eaee/profile.jpg", "Mason Miller"]], "46352": [["/thumb/070ca/profile.jpg", "Deven Lee"]], "45488": [["/thumb/9e1a5/profile.jpg", "Anya Rodriquez"]], "113088": [["/thumb/914ca/profile.jpg", "Madison Jackson"]], "52160": [["/thumb/92f60/profile.jpg", "Barbara Miller"]], "67456": [["/thumb/4d26a/profile.jpg", "Deven Thomas"]], "75888": [["/thumb/efa4d/profile.jpg", "Joseph Brown"]], "50736": [["/thumb/31baa/profile.jpg", "James Lopez"]], "28272": [["/thumb/ba8f3/profile.jpg", "Mason Jackson"]], "70032": [["/thumb/b8ab7/profile.jpg", "Olivia Lopez"]], "76416": [["/thumb/64a5c/profile.jpg", "Santiago Garcia"]], "91712": [["/thumb/a10e8/profile.jpg", "Jayden Lopez"], ["/thumb/09dd1/profile.jpg", "Mary White"]], "49152": [["/thumb/ceb35/profile.jpg", "Liam Jackson"]], "85360": [["/thumb/244b3/profile.jpg", "Ethan Davis"]], "111840": [["/thumb/1ddb9/profile.jpg", "John White"]], "31456": [["/thumb/f058f/profile.jpg", "Sofia Martinez"]], "103792": [["/thumb/53c99/profile.jpg", "Mary Smith"]], "107472": [["/thumb/6f4b6/profile.jpg", "Ethan Williams"]], "72304": [["/thumb/6d547/profile.jpg", "Anya Jones"]], "60672": [["/thumb/1a2f9/profile.jpg", "Shreya Taylor"]], "93712": [["/thumb/8d724/profile.jpg", "Mason Taylor"]], "76896": [["/thumb/f6e03/profile.jpg", "Madison Moore"]], "105952": [["/thumb/04cf6/profile.jpg", "David Martin"]], "41936": [["/thumb/865ef/profile.jpg", "Emily Martin"]], "53744": [["/thumb/3f377/profile.jpg", "Barbara Brown"]], "73632": [["/thumb/b7f8c/profile.jpg", "Anya Moore"]], "228544": [["/thumb/4a18b/profile.jpg", "Ava Martinez"]], "42896": [["/thumb/21b94/profile.jpg", "Emma Jackson"]], "73888": [["/thumb/3b5ef/profile.jpg", "Deven Moore"]]}